envmodule.py
envModule-0.0.3.dist-info/LICENSE
envModule-0.0.3.dist-info/METADATA
envModule-0.0.3.dist-info/WHEEL
envModule-0.0.3.dist-info/top_level.txt
envModule-0.0.3.dist-info/RECORD
