Metadata-Version: 2.1
Name: envModule
Version: 0.0.3
Summary: Library to read .env files
Home-page: UNKNOWN
Author: Mansur Uldanov
Author-email: uldanovmansur2005@gmail.com
License: UNKNOWN
Platform: UNKNOWN
Classifier: Programming Language :: Python :: 3
Classifier: License :: OSI Approved :: MIT License
Classifier: Operating System :: OS Independent
Requires-Python: >=3.6
License-File: LICENSE
